cpct/__about__.py
cpct/__init__.py
cpct/base_types.py
cpct/cpct.py
cpct/cpct_START_HERE.cmd
cpct/cpct_download.bat
cpct/cpct_install_requirements.py
cpct/discord.py
cpct/poepy.py
cpct/user_info.py
cpct/img/ChipyLogo.png
cpct/img/ChipyLogo.psd
cpct/img/cpct_logo.png
cpct/img/ctcp_gui.png
cpct/img/dropper.png
cpct/img/poe.png
cpct/qt/build_gui.bat
cpct/qt/main_gui.py
cpct/qt/main_gui.ui
cpct/qt/stash_overlay.py
cpct/qt/stash_overlay.ui
cpct-0.2.1.dist-info/METADATA
cpct-0.2.1.dist-info/WHEEL
cpct-0.2.1.dist-info/licenses/LICENSE.txt
cpct-0.2.1.dist-info/RECORD
