Metadata-Version: 2.1
Name: cpct
Version: 0.2.1
Summary: Chipys PathOfExile Chaos Tool
Project-URL: Documentation, https://github.com/unknown/cpct#readme
Project-URL: Issues, https://github.com/unknown/cpct/issues
Project-URL: Source, https://github.com/unknown/cpct
Author-email: Chipy <iamchipy@gmail.com>
License-Expression: MIT
License-File: LICENSE.txt
Keywords: Chaos Recipe,Chipy,PathOfExile,PoE
Classifier: Development Status :: 4 - Beta
Classifier: Programming Language :: Python
Classifier: Programming Language :: Python :: 3.7
Classifier: Programming Language :: Python :: 3.8
Classifier: Programming Language :: Python :: 3.9
Classifier: Programming Language :: Python :: 3.10
Classifier: Programming Language :: Python :: 3.11
Classifier: Programming Language :: Python :: Implementation :: CPython
Classifier: Programming Language :: Python :: Implementation :: PyPy
Requires-Python: >=3.7
Requires-Dist: psutil
Requires-Dist: pyautogui
Requires-Dist: pyqt
Requires-Dist: pyqt5
Requires-Dist: pywinauto
Requires-Dist: requests
Requires-Dist: websockets
